{
    "clientToken": "serviceB.2",
    
    "routeName": "serviceB-route",
    "spec": {
        "httpRoute": {
            "action": {
                "weightedTargets": [
                    {
                        "virtualNode": "serviceBv1",
                        "weight": 50
                    },
                    {
                        "virtualNode": "serviceBv2",
                        "weight": 50
                    }
                ]
            },
            "match": {
                "prefix": "/"
            }
        }
    },
    "virtualRouterName": "serviceB"
}